leaflet/__init__.py
leaflet/admin.py
leaflet/apps.py
leaflet/utils.py
leaflet/forms/__init__.py
leaflet/forms/fields.py
leaflet/forms/widgets.py
leaflet/locale/cs/LC_MESSAGES/django.mo
leaflet/locale/de/LC_MESSAGES/django.mo
leaflet/locale/es/LC_MESSAGES/django.mo
leaflet/locale/fr/LC_MESSAGES/django.mo
leaflet/locale/he/LC_MESSAGES/django.mo
leaflet/locale/hu/LC_MESSAGES/django.mo
leaflet/locale/it/LC_MESSAGES/django.mo
leaflet/locale/ru/LC_MESSAGES/django.mo
leaflet/locale/sk/LC_MESSAGES/django.mo
leaflet/static/leaflet/Control.MiniMap.css
leaflet/static/leaflet/Control.MiniMap.js
leaflet/static/leaflet/leaflet-src.js
leaflet/static/leaflet/leaflet-src.js.map
leaflet/static/leaflet/leaflet.css
leaflet/static/leaflet/leaflet.extras.css
leaflet/static/leaflet/leaflet.extras.js
leaflet/static/leaflet/leaflet.forms.js
leaflet/static/leaflet/leaflet.js
leaflet/static/leaflet/leaflet.js.map
leaflet/static/leaflet/leaflet_django.css
leaflet/static/leaflet/proj4.js
leaflet/static/leaflet/proj4leaflet.js
leaflet/static/leaflet/draw/leaflet.draw-src.css
leaflet/static/leaflet/draw/leaflet.draw-src.js
leaflet/static/leaflet/draw/leaflet.draw-src.map
leaflet/static/leaflet/draw/leaflet.draw.css
leaflet/static/leaflet/draw/leaflet.draw.i18n.js
leaflet/static/leaflet/draw/leaflet.draw.js
leaflet/static/leaflet/draw/images/layers-2x.png
leaflet/static/leaflet/draw/images/layers.png
leaflet/static/leaflet/draw/images/marker-icon-2x.png
leaflet/static/leaflet/draw/images/marker-icon.png
leaflet/static/leaflet/draw/images/marker-shadow.png
leaflet/static/leaflet/draw/images/spritesheet-2x.png
leaflet/static/leaflet/draw/images/spritesheet.png
leaflet/static/leaflet/draw/images/spritesheet.svg
leaflet/static/leaflet/images/layers-2x.png
leaflet/static/leaflet/images/layers.png
leaflet/static/leaflet/images/marker-icon-2x.png
leaflet/static/leaflet/images/marker-icon.png
leaflet/static/leaflet/images/marker-icon@2x.png
leaflet/static/leaflet/images/marker-shadow.png
django_leaflet-0.30.1.dist-info/LICENSE
django_leaflet-0.30.1.dist-info/METADATA
django_leaflet-0.30.1.dist-info/WHEEL
django_leaflet-0.30.1.dist-info/top_level.txt
django_leaflet-0.30.1.dist-info/RECORD
